cheez_ppg_pico/__init__.py
cheez_ppg_pico/port_manager.py
cheez_ppg_pico/serial_decoder.py
cheez_ppg_pico-1.0.1.dist-info/METADATA
cheez_ppg_pico-1.0.1.dist-info/WHEEL
cheez_ppg_pico-1.0.1.dist-info/top_level.txt
cheez_ppg_pico-1.0.1.dist-info/RECORD
