Metadata-Version: 2.1
Name: cheez-ppg-pico
Version: 1.0.1
Summary: SDK for CheezPico(PPG) USB/BLE Devices
Author: vecang
Classifier: Development Status :: 3 - Alpha
Classifier: Intended Audience :: Developers
Classifier: License :: OSI Approved :: MIT License
Classifier: Programming Language :: Python :: 3.7
Classifier: Programming Language :: Python :: 3.8
Classifier: Programming Language :: Python :: 3.9
Requires-Python: >=3.7
Requires-Dist: pyserial
Requires-Dist: aioserial
